[
    {
        "title": "Book Shelf",
        "auther": "James Bookman",
        "tags": "furniture" 
    },
    {
        "title": "Desk Orginizer",
        "auther": "3dMaster",
        "tags": ["furniture", "desk"] 
    },
    {
        "title": "Macro-Controller",
        "auther": "3dMaster",
        "tags": ["furniture", "desk"] 
    },
    {
        "title": "Custome Logo",
        "auther": "Deyan Soosai",
        "tags": ["other"]
    },
    {
        "title": "Car",
        "auther": "Deyan Soosai",
        "tags": ["desk", "models"]
    },
    {
        "title": "Wire Holder",
        "auther": "ComputerGuy",
        "tags": ["desk"]
    },
    {
        "title": "Fan",
        "auther":"Deyan Soosai",
        "tags": ["desk", "other"]
    }
]